estnltk_core/__init__.py
estnltk_core/base_text.py
estnltk_core/common.py
estnltk_core/layer_resolver.py
estnltk_core/taggers_registry.py
estnltk_core/converters/__init__.py
estnltk_core/converters/default_serialisation.py
estnltk_core/converters/dict_exporter.py
estnltk_core/converters/dict_importer.py
estnltk_core/converters/json_converter.py
estnltk_core/converters/json_exporter.py
estnltk_core/converters/json_importer.py
estnltk_core/converters/layer_dict_converter.py
estnltk_core/converters/records_converter.py
estnltk_core/converters/relation_layer_serialisation_v0.py
estnltk_core/converters/relation_layer_serialisation_v1.py
estnltk_core/converters/serialisation_registry.py
estnltk_core/converters/unicode_binary.py
estnltk_core/layer/__init__.py
estnltk_core/layer/annotation.py
estnltk_core/layer/base_layer.py
estnltk_core/layer/base_span.py
estnltk_core/layer/enveloping_span.py
estnltk_core/layer/layer.py
estnltk_core/layer/relation_layer.py
estnltk_core/layer/span.py
estnltk_core/layer/span_list.py
estnltk_core/layer/span_operations.py
estnltk_core/layer/to_html.py
estnltk_core/layer/attribute_list/__init__.py
estnltk_core/layer/attribute_list/ambiguous_attribute_list.py
estnltk_core/layer/attribute_list/ambiguous_attribute_tuple_list.py
estnltk_core/layer/attribute_list/attribute_list.py
estnltk_core/layer/attribute_list/attribute_tuple_list.py
estnltk_core/layer/attribute_list/immutable_list.py
estnltk_core/layer_operations/__init__.py
estnltk_core/layer_operations/conflict_resolver.py
estnltk_core/layer_operations/diff.py
estnltk_core/layer_operations/flatten.py
estnltk_core/layer_operations/layer_dependencies.py
estnltk_core/layer_operations/layer_indexing.py
estnltk_core/layer_operations/rebase.py
estnltk_core/layer_operations/aggregators/__init__.py
estnltk_core/layer_operations/aggregators/groupby.py
estnltk_core/layer_operations/aggregators/rolling.py
estnltk_core/layer_operations/combiners/__init__.py
estnltk_core-1.7.3.dist-info/LICENSE
estnltk_core-1.7.3.dist-info/METADATA
estnltk_core-1.7.3.dist-info/WHEEL
estnltk_core-1.7.3.dist-info/top_level.txt
estnltk_core-1.7.3.dist-info/RECORD
