Metadata-Version: 2.1
Name: estnltk_core
Version: 1.7.3
Summary: EstNLTK core - basic data structures and components of the EstNLTK library
Home-page: https://github.com/estnltk/estnltk
Author: University of Tartu
Author-email: Siim Orasmaa <siim.orasmaa@ut.ee>, Sven Laur <swen@math.ut.ee>, Paul Tammo <paul.tammo@gmail.com>
License: GPLv2
Project-URL: homepage, https://github.com/estnltk/estnltk
Project-URL: documentation, https://github.com/estnltk/estnltk/tree/main/tutorials
Project-URL: repository, https://github.com/estnltk/estnltk/tree/main/estnltk_core
Project-URL: changelog, https://github.com/estnltk/estnltk/blob/main/CHANGELOG.md
Keywords: natural language processing data structures,linguistic processing data structures
Classifier: Intended Audience :: Developers
Classifier: Intended Audience :: Education
Classifier: Intended Audience :: Science/Research
Classifier: Intended Audience :: Information Technology
Classifier: Operating System :: OS Independent
Classifier: Programming Language :: Python :: 3.9
Classifier: Programming Language :: Python :: 3.10
Classifier: Programming Language :: Python :: 3.11
Classifier: Programming Language :: Python :: 3.12
Classifier: Topic :: Scientific/Engineering
Classifier: Topic :: Scientific/Engineering :: Artificial Intelligence
Classifier: Topic :: Scientific/Engineering :: Information Analysis
Classifier: Topic :: Text Processing
Classifier: Topic :: Text Processing :: Linguistic
Requires-Python: >=3.9
License-File: LICENSE
Requires-Dist: regex >=2015.07.19
Requires-Dist: networkx
Requires-Dist: pandas
Provides-Extra: tests
Requires-Dist: pytest ; extra == 'tests'
